outlier_removal/outlier.py
outlier_removal_101703297-1.0.dist-info/LICENSE
outlier_removal_101703297-1.0.dist-info/METADATA
outlier_removal_101703297-1.0.dist-info/WHEEL
outlier_removal_101703297-1.0.dist-info/entry_points.txt
outlier_removal_101703297-1.0.dist-info/top_level.txt
outlier_removal_101703297-1.0.dist-info/RECORD
