Metadata-Version: 2.1
Name: outlier-removal-101703297
Version: 1.0
Summary: A Python package for removing outliers in dataset using the Interquartile Range technique.
Home-page: https://github.com/kanchitbajaj8070/outlier-removal-101703297
Author: kunal bajaj
Author-email: kanchitbajaj8070@gmail.com
License: MIT
Platform: UNKNOWN
Classifier: License :: OSI Approved :: MIT License
Classifier: Programming Language :: Python :: 3
Classifier: Programming Language :: Python :: 3.7
Requires-Dist: pandas
Requires-Dist: numpy
